sysexits/__init__.py
sysexits/_version.py
sysexits-0.5.0.dist-info/LICENSE
sysexits-0.5.0.dist-info/METADATA
sysexits-0.5.0.dist-info/WHEEL
sysexits-0.5.0.dist-info/top_level.txt
sysexits-0.5.0.dist-info/RECORD
