Metadata-Version: 2.1
Name: sysexits
Version: 0.5.0
Summary: simple python wrapper around FreeBSD sysexits
Home-page: https://github.com/chris-mcdo/sysexits
Author: Christopher McDonald
Author-email: cmcdonal33@gmail.com
License: MIT
Project-URL: Source, https://github.com/chris-mcdo/sysexits
Project-URL: Tracker, https://github.com/chris-mcdo/sysexits/issues
Keywords: freebsd,exit,error,wrapper
Platform: win32
Platform: linux
Platform: osx
Classifier: Development Status :: 4 - Beta
Classifier: Intended Audience :: Developers
Classifier: License :: OSI Approved :: MIT License
Classifier: Operating System :: MacOS :: MacOS X
Classifier: Operating System :: Microsoft :: Windows
Classifier: Operating System :: POSIX
Classifier: Programming Language :: Python :: 3
Classifier: Programming Language :: Python :: 3 :: Only
Classifier: Programming Language :: Python :: 3.5
Classifier: Programming Language :: Python :: 3.6
Classifier: Programming Language :: Python :: 3.7
Classifier: Programming Language :: Python :: 3.8
Classifier: Programming Language :: Python :: 3.9
Classifier: Programming Language :: Python :: 3.10
Requires-Python: >=3.5
License-File: LICENSE
